dFL/__init__.py
dFL/MainServer/__init__.py
dFL/MainServer/api.py
dFL/MainServer/handlers.py
dFL/MainServer/models.py
dFL/MainServer/Handlers/__init__.py
dFL/MainServer/Handlers/fl_handler.py
dFL/MainServer/Handlers/node_handler.py
dFL/MainServer/Handlers/process_handler.py
dFL/MainServer/keys/private_key_encryption.pem
dFL/MainServer/keys/private_key_signature.pem
dFL/MainServer/keys/public_key_encryption.pem
dFL/MainServer/keys/public_key_signature.pem
dFL/Peer/__init__.py
dFL/Peer/client.py
dFL/Peer/node.py
dFL/Peer/registration.py
dFL/Peer/server.py
dFL/Processes/__init__.py
dFL/Processes/fl.py
dFL/Security/__init__.py
dFL/Security/communication.py
dFL/Security/crypto.py
dFL/Security/files.py
dFL/Utils/__init__.py
dFL/Utils/config.py
dFL/Utils/keys.py
dFL/Utils/util.py
dFL-0.0.1.dist-info/LICENSE.txt
dFL-0.0.1.dist-info/METADATA
dFL-0.0.1.dist-info/WHEEL
dFL-0.0.1.dist-info/top_level.txt
dFL-0.0.1.dist-info/RECORD
